SalamFake/SalamFake.py
SalamFake/__init__.py
SalamFake/message.py
SalamFake-1.0.2.dist-info/LICENSE
SalamFake-1.0.2.dist-info/METADATA
SalamFake-1.0.2.dist-info/WHEEL
SalamFake-1.0.2.dist-info/top_level.txt
SalamFake-1.0.2.dist-info/RECORD
